django_password_protect
