Metadata-Version: 1.0
Name: Django-Password-Protect
Version: 0.0.3
Summary: Middleware to add BasicAuth password protection to a site
Home-page: https://github.com/plumdog/django-password-protect
Author: Andrew Plummer
Author-email: plummer574@gmail.com
License: UNKNOWN
Platform: UNKNOWN
